hyanova/__init__.py
hyanova/hyanova.py
hyanova-1.1.2.dist-info/LICENSE
hyanova-1.1.2.dist-info/METADATA
hyanova-1.1.2.dist-info/WHEEL
hyanova-1.1.2.dist-info/top_level.txt
hyanova-1.1.2.dist-info/RECORD
