Metadata-Version: 2.1
Name: hyanova
Version: 1.1.2
Summary: A pure python implementation of fuctional ANOVA algorithm.
Home-page: https://github.com/exiarepairii/hyanova
Author: Su Qiao
Author-email: qiaosu98@outlook.com
License: MIT
Keywords: anova,sklearn,hyperparameter,hyperparameter importance
Platform: any
Requires-Python: >=3.6
Requires-Dist: numpy
Requires-Dist: pandas
Requires-Dist: tqdm
